jpy_tillo_sdk/__init__.py
jpy_tillo_sdk/contracts.py
jpy_tillo_sdk/endpoint.py
jpy_tillo_sdk/enums.py
jpy_tillo_sdk/errors.py
jpy_tillo_sdk/http_client.py
jpy_tillo_sdk/http_client_factory.py
jpy_tillo_sdk/http_methods.py
jpy_tillo_sdk/rate_limits.py
jpy_tillo_sdk/signature.py
jpy_tillo_sdk/tillo.py
jpy_tillo_sdk/domain/__init__.py
jpy_tillo_sdk/domain/brand/__init__.py
jpy_tillo_sdk/domain/brand/endpoints.py
jpy_tillo_sdk/domain/brand/services.py
jpy_tillo_sdk/domain/digital_card/__init__.py
jpy_tillo_sdk/domain/digital_card/endpoints.py
jpy_tillo_sdk/domain/digital_card/services.py
jpy_tillo_sdk/domain/digital_card/shared.py
jpy_tillo_sdk/domain/float/__init__.py
jpy_tillo_sdk/domain/float/endpoints.py
jpy_tillo_sdk/domain/float/services.py
jpy_tillo_sdk/domain/physical_card/__init__.py
jpy_tillo_sdk/domain/physical_card/endpoints.py
jpy_tillo_sdk/domain/physical_card/services.py
jpy_tillo_sdk/domain/physical_card/shared.py
jpy_tillo_sdk/domain/webhook/__init__.py
jpy_tillo_sdk/domain/webhook/enums.py
jpy_tillo_sdk/domain/webhook/handlers.py
jpy_tillo_sdk/domain/webhook/models.py
jpy_tillo_sdk/domain/webhook/services.py
jpy_tillo_sdk-0.3.0.dist-info/METADATA
jpy_tillo_sdk-0.3.0.dist-info/WHEEL
jpy_tillo_sdk-0.3.0.dist-info/licenses/LICENSE
jpy_tillo_sdk-0.3.0.dist-info/RECORD
