Metadata-Version: 2.4
Name: jpy-tillo-sdk
Version: 0.3.0
Summary: The package for developers to interact with the Tillo APIv2
Project-URL: Homepage, https://github.com/jaddek/jpy-tillo-sdk
Project-URL: Issues, https://github.com/jaddek/jpy-tillo-sdk/issues
Author-email: Anton Nazarov <tonynazarov@gmail.com>
License-Expression: MIT
License-File: LICENSE
Requires-Python: >=3.10
Requires-Dist: black>=25.1.0
Requires-Dist: coverage>=7.8.0
Requires-Dist: httpx[http2]<0.29.0,>=0.28.1
Requires-Dist: mypy>=1.15.0
